{"id": "b4df0905-8eac-4b44-a953-d8508258de10", "code": "def initial_reward_function(env, prev_state, curr_state) -> float:\n    \"\"\"\n    Initial reward seed for FrozenLake OpenEvolve search.\n\n    Expected state keys:\n    - manhattan_to_goal\n    - delta_manhattan\n    - on_goal\n    - fell_in_hole\n    - terminated\n    \"\"\"\n    reward = 0.0\n    reward += 0.15 * float(curr_state[\"delta_manhattan\"])\n    reward -= 0.01 * float(curr_state[\"manhattan_to_goal\"])\n\n    if curr_state[\"on_goal\"] > 0.5:\n        reward += 1.0\n    if curr_state[\"fell_in_hole\"] > 0.5:\n        reward -= 1.0\n    if curr_state[\"terminated\"] < 0.5:\n        reward -= 0.005\n    return float(reward)\n", "changes_description": "", "language": "python", "parent_id": null, "generation": 0, "timestamp": 1777480085.5736382, "iteration_found": 0, "metrics": {"combined_score": 9.840924049326647, "best_true_reward": 0.06666666666666667, "avg_true_reward": 0.024999999999999998, "stability": 0.976800738265998, "budget_efficiency": 1.007996774410322, "budget_used": 119048.0, "round_count": 32.0, "active_arms_final": 2.0, "early_stop_triggered": 0.0, "valid": 1.0, "selected_strategy": 1.0, "stage_scale": 1.0, "comparison_mode": 1.0, "stage1_passed": 1.0, "stage2_passed": 1.0, "stage3_passed": 1.0}, "complexity": 0.0, "diversity": 0.0, "metadata": {"island": 0}, "prompts": null, "artifacts_json": null, "artifact_dir": null, "embedding": null}